README.md
setup.py
jobstamps/__init__.py
jobstamps/jobstamp.py
jobstamps/jobstamp_cmd_main.py
jobstamps.egg-info/PKG-INFO
jobstamps.egg-info/SOURCES.txt
jobstamps.egg-info/dependency_links.txt
jobstamps.egg-info/entry_points.txt
jobstamps.egg-info/requires.txt
jobstamps.egg-info/top_level.txt
jobstamps.egg-info/zip-safe
test/test_jobstamp_cmd_main.py
test/test_jobstamps.py
test/testutil.py